pymovie/NE3Lut.p
pymovie/PyMovie-doc.pdf
pymovie/PyMovie-info.pdf
pymovie/PyMovie.bat
pymovie/SER.py
pymovie/__init__.py
pymovie/alias_lnk_resolver.py
pymovie/aperture.py
pymovie/apertureEdit.py
pymovie/apertureEditDialog.py
pymovie/apertureNameDialog.py
pymovie/aperturesFileTagDialog.py
pymovie/astrometry_client.py
pymovie/astropyStarExtractionBackgound.py
pymovie/checkForNewerVersion.py
pymovie/gammaUtils.py
pymovie/gui.py
pymovie/helpDialog.py
pymovie/hotPixelDialog.py
pymovie/main.py
pymovie/ocr.py
pymovie/ocrCharacterBox.py
pymovie/ocrProfileNameDialog.py
pymovie/play-Temp.py
pymovie/play-introspection.py
pymovie/run-pymovie-mac.bat
pymovie/selectHotPixelProfile.py
pymovie/selectProfile.py
pymovie/stacker.py
pymovie/starPositionDialog.py
pymovie/version.py
pymovie/wcs_helper_functions.py
pymovie-4.1.5.dist-info/LICENSE
pymovie-4.1.5.dist-info/METADATA
pymovie-4.1.5.dist-info/WHEEL
pymovie-4.1.5.dist-info/top_level.txt
pymovie-4.1.5.dist-info/RECORD
