Metadata-Version: 2.1
Name: pymovie
Version: 4.1.5
Summary: pymovie is a lightcurve extractor for astronomical videos
Home-page: https://github.com/bob-anderson-ok/pymovie
Author: Bob Anderson
Author-email: bob.anderson.ok@gmail.com
Maintainer: Bob Anderson
Maintainer-email: bob.anderson.ok@gmail.com
License: License :: OSI Approved :: MIT License
Keywords: desktop app,lightcurve extraction from astronomical videos
Classifier: Development Status :: 5 - Production/Stable
Classifier: Intended Audience :: Science/Research
Classifier: Natural Language :: English
Classifier: License :: OSI Approved :: MIT License
Classifier: Operating System :: MacOS :: MacOS X
Classifier: Operating System :: Microsoft :: Windows
Classifier: Operating System :: POSIX :: Linux
Classifier: Programming Language :: Python :: 3.7
Classifier: Programming Language :: Python :: Implementation :: CPython
Classifier: Topic :: Scientific/Engineering
Requires-Python: >=3.7
License-File: LICENSE
Requires-Dist: pyqtgraph==0.12.4
Requires-Dist: ravf
Requires-Dist: opencv-python
Requires-Dist: astroquery
Requires-Dist: resource
Requires-Dist: scikit-image>=0.15.0
Requires-Dist: wheel
Requires-Dist: requests
Requires-Dist: pyephem
Requires-Dist: winshell; platform_system == "Windows"
Requires-Dist: pypiwin32; platform_system == "Windows"
Requires-Dist: matplotlib
Requires-Dist: numpy<=1.23.1
Requires-Dist: astropy
Requires-Dist: scikit-image
Requires-Dist: scipy
Requires-Dist: numba>=0.41.0
Requires-Dist: Adv2>=1.2.0
Requires-Dist: PyQt5
Requires-Dist: more_itertools
